{
  "addons": [
    {
      "title": "Magisk",
      "summary": "Magisk",
      "url": "http://tiny.cc/latestmagisk"
    },
    {
      "title": "Magisk",
      "summary": "Magisk Uninstaller",
      "url": "http://tiny.cc/latestuninstaller"
    }
  ],
  
  "filename": "LEGIONOS-1.7-rimo02a-OFFICIAL-20190713-1104.zip",
  "changelog": "- Updated LegionOS to 1.7\n- Clear all notif change a bit and fix leftover glitch\n- Android Q style Wifi icons (Evolution X version)\n- Add Back manage notif to statusbar footer\n-  Settings: Changes from Android Q Beta 4 with various icons\n- Change default wallpaper\n- Performance improvements\n-  Telephony: Stop using rssnr, it falsly shows wrong signal bars\n- Add Smart Charging\n- SystemUI: Protect against terrible music players\n- base: Import Android Q animations\n- Move Q animation to custom animations\n- Q seekbar: Stable seek bar positioning\n- core: os: Build: Don't fail consistency check if vendor is mismatched\n Add 18 more QS styles",
  "filesize": "597513191",
  "md5": "0aeb948d6c769ea04a5cad49a637c9a7",
  "build_date": "20190713",
  "device": "rimo02a",
  "url": "https://sourceforge.net/projects/legionrom/files/rimo02a/LEGIONOS-1.7-rimo02a-OFFICIAL-20190713-1104.zip/download",

  "donate_url": "https://paypal.me/rajkale99",
  "developer_url": "http://github.com/rajkale99",
  "news_url": "https://t.me/LegionUpdates",
  "developer": "Prashant",
  "error": "false",
  "website_url": "https://legionos.ml",
  "forum_url": "",
  "device_brand": "Smartron",
  "device_model": "Smartron Srt"
}
